orf/OrderedForest.py
orf/_BaseOrderedForest.py
orf/_OrderedRandomForest.py
orf/__init__.py
orf/_utils.py
orf-0.2.0.dist-info/LICENSE.txt
orf-0.2.0.dist-info/METADATA
orf-0.2.0.dist-info/WHEEL
orf-0.2.0.dist-info/top_level.txt
orf-0.2.0.dist-info/RECORD
