Metadata-Version: 2.1
Name: orf
Version: 0.2.0
Summary: orf package implements the Ordered Forest estimator for random forest estimation of the ordered choice models.
Home-page: https://orf-lab.github.io
Author: Michael Lechner, Fabian Muny & Gabriel Okasa
Author-email: fabian.muny@unisg.ch
License: MIT
Download-URL: https://github.com/fmuny/ORFpy/archive/refs/tags/v0.2.0.tar.gz
Keywords: ordered forest,ordered choice,random forest
Platform: UNKNOWN
Classifier: Development Status :: 4 - Beta
Classifier: Intended Audience :: Science/Research
Classifier: Topic :: Software Development :: Build Tools
Classifier: License :: OSI Approved :: MIT License
Classifier: Programming Language :: Python :: 3.8
Classifier: Programming Language :: Python :: 3.9
Classifier: Programming Language :: Python :: 3.10
License-File: LICENSE.txt
Requires-Dist: numpy (>=1.21.0)
Requires-Dist: pandas (>=1.3.5)
Requires-Dist: scipy (>=1.7.2)
Requires-Dist: scikit-learn (>=1.0.2)
Requires-Dist: joblib (>=1.0.1)
Requires-Dist: plotnine (>=0.8.0)
